polip/__init__.py
polip/module.py
polip-0.3.dist-info/LICENSE
polip-0.3.dist-info/METADATA
polip-0.3.dist-info/WHEEL
polip-0.3.dist-info/top_level.txt
polip-0.3.dist-info/RECORD
