Metadata-Version: 2.1
Name: polip
Version: 0.3
Home-page: https://github.com/dykyivladk1/polip
Author: Vladyslav
Author-email: vladdikiy17@gmai.com
License: MIT
License-File: LICENSE
